travecto/__init__.py
travecto/cli.py
travecto/config_loader.py
travecto/directions.py
travecto/geocoder.py
travecto/planner.py
travecto/server.py
travecto/solver.py
travecto/utils.py
travecto/visualizer.py
travecto-2025.8.19.dist-info/licenses/LICENSE
travecto-2025.8.19.dist-info/METADATA
travecto-2025.8.19.dist-info/WHEEL
travecto-2025.8.19.dist-info/entry_points.txt
travecto-2025.8.19.dist-info/top_level.txt
travecto-2025.8.19.dist-info/RECORD
