Metadata-Version: 2.4
Name: travecto
Version: 2025.8.19
Summary: Optimizes travel routes using Google Maps Geocoding API and the traveling salesman problem solver from OR-Tools.
Author: Inc44
License-Expression: MIT
Project-URL: Repository, https://github.com/Inc44/Travecto.git
Project-URL: Issues, https://github.com/Inc44/Travecto/issues
Classifier: Operating System :: OS Independent
Classifier: Programming Language :: Python :: 3
Classifier: Programming Language :: Python :: 3.9
Classifier: Programming Language :: Python :: 3.10
Classifier: Programming Language :: Python :: 3.11
Classifier: Programming Language :: Python :: 3.12
Classifier: Programming Language :: Python :: 3.13
Requires-Python: >=3.9
License-File: LICENSE
Requires-Dist: aiohttp==3.12.15
Requires-Dist: fastapi==0.116.1
Requires-Dist: folium==0.20.0
Requires-Dist: ortools==9.14.6206
Requires-Dist: python-dotenv==1.1.1
Requires-Dist: tenacity==9.1.2
Requires-Dist: toml==0.10.2
Requires-Dist: tqdm==4.67.1
Requires-Dist: uvicorn==0.35.0
Dynamic: license-file
